jupyterlab_server_timer/__init__.py
jupyterlab_server_timer/_version.py
jupyterlab_server_timer/handlers.py
jupyterlab_server_timer/tests/__init__.py
jupyterlab_server_timer/tests/test_handlers.py
jupyterlab_server_timer-0.1.3.data/data/etc/jupyter/jupyter_server_config.d/jupyterlab_server_timer.json
jupyterlab_server_timer-0.1.3.data/data/share/jupyter/labextensions/jupyterlab-server-timer/package.json
jupyterlab_server_timer-0.1.3.data/data/share/jupyter/labextensions/jupyterlab-server-timer/static/512.ca91dd4171d250ddcf01.js
jupyterlab_server_timer-0.1.3.data/data/share/jupyter/labextensions/jupyterlab-server-timer/static/736.abd4b8771fb4d31ae79a.js
jupyterlab_server_timer-0.1.3.data/data/share/jupyter/labextensions/jupyterlab-server-timer/static/remoteEntry.ba1fd6b269b8d83d1037.js
jupyterlab_server_timer-0.1.3.data/data/share/jupyter/labextensions/jupyterlab-server-timer/static/style.js
jupyterlab_server_timer-0.1.3.data/data/share/jupyter/labextensions/jupyterlab-server-timer/static/third-party-licenses.json
jupyterlab_server_timer-0.1.3.data/data/share/jupyter/labextensions/jupyterlab-server-timer/install.json
jupyterlab_server_timer-0.1.3.dist-info/METADATA
jupyterlab_server_timer-0.1.3.dist-info/WHEEL
jupyterlab_server_timer-0.1.3.dist-info/licenses/LICENSE
jupyterlab_server_timer-0.1.3.dist-info/RECORD
